<?xml version="1.0" encoding="utf-8"?><Search><pages Count="14"><page Index="1"><![CDATA[¡Checa nuestro



                                               menú online!















                @restaurantelaveintitres


                restaurantelaveintitres@gmail.com]]></page><page Index="2"><![CDATA[Desayunos











          HUEVOS AL GUSTO - $60
          Omelette, divorciados, rancheras, revueltos
          o estrellados.

          HUEVOS AL EDÉN - $50
          Huevo estrellado cobijado con una hoja
          santa, bañado en salsa verde, acompañado
          de frijoles.


          MOLLETES - $45
          Acompañados de ensalada de la casa.

          ENCHILADAS SUIZAS - $70
          Enchiladas rellenas de pollo gratinadas con
          queso gouda y bañadas en salsa cremosa
          de tomate.















                                                           CHILAQUILES ROJOS - $60
                                                           Chilaquiles acompañados de una pieza de huevo o
                                                           pollo, frijoles y ensalada.

                                                           CHILAQUILES VERDES - $60
                                                           Chilaquiles acompañados de una pieza de huevo o
                                                           pollo, frijoles y ensalada.

                                                           CHILAQUILES DE CREMA DE POBLANO - $80
                                                           Chilaquiles bañados con una crema de poblano
                                                           acompañados de una pieza de huevo o pollo,
                                                           frijoles y ensalada.]]></page><page Index="3"><![CDATA[Desayunos














         CHILAQUILES DE CREMA DE CACAHUATE - $80
         Chilaquiles bañados en una crema de cacahuate
         acompañados de una pieza de huevo o pollo, frijoles y
         ensalada.

         COMPLEMENTOS EXTRAS PARA CHILAQUILES
         • POLLO A LA PLANCHA - $20
         • ARRACHERA $30 HUEVO EXTRA - $15





























         CROQUE MADAME - $70
         Emparedado de jamón, gratinado con
         queso gouda, y bañado en una crema
         con un toque de nuez moscada, con
         guarnición de ensalada.


         CROQUE MONSIEUR - $80
         Emparedado de jamón y huevo estrellado
         o revuelto, gratinado con queso gouda,
         y bañado en una crema con un toque
         de nuez moscada, con guarnición de
         ensalada.]]></page><page Index="4"><![CDATA[Desayunos
















































               HOT CAKES - $50
               Acompañados con fruta de temporada, mermelada miel o maple.


               PAN FRANCÉS - $70
               Tradicional pan francés acompañado con frutas de temporada, y una compota de
               manzana receta de la casa.


               BOWL DE FRUTAS DE TEMPORADA - $70
               Mix de frutas de temporadas acompañado con yogurt, granola y miel.






                HORARIO DE DESAYUNOS ES DE 8:00AM A 1:00PM]]></page><page Index="5"><![CDATA[Entradas









                   TUÉTANOS (2pz) - $80
                   Tuétano al grill con Chimichurri tradicional argentino y un toque
                   cremoso de Aguacate.


                   JALAPEÑOS ARREBOZADOS (2pz) - $75
                   Rebosados en Tempura y rellenos de Queso, bañados en Salsa
                   Teriyaki y acompañados de Mayonesa de Ajo tatemado.


                   PAPAS GAJO - $70
                   Bañadas en Queso Cheddar y Mermelada de tocino
                   receta de la casa.


                   TOSTADAS DE AGUACHILE (2pz) - $90
                   Tiritas de Pescado con Aguachile verde tradicional o de Sandia y
                   Fresa, sobre un Buñuelo, Pepino, Cebolla y Aguacate.

                   TIRADITO DE SALMÓN - $90
                   Laminas delgadas de Salmón marinadas con Salsa Napolitana y
                   espolvoreado con Queso Parmesano.

                   GUACAMOLE CALAVERA - $80
                   Tradicional guacamole, con un Giro de Tropezones de Fresa y
                   Queso de Cabra]]></page><page Index="6"><![CDATA[Ensaladas

















































                  ENSALADA DE MANZANA A LA PARRILLA - $70


                  Mix de Lechugas, Crotones, Queso Panela, Nuez y Jitomate Cherry,
                  con Aderezo de Vinagre Balsámico.

                  ENSALADA DE FRUTOS SECOS - $70


                  Mix de Lechugas con una combinación de Fruta confitada y Frutos
                  secos, con Aderezo de Ate.


                  ENSALADA MEDITERRÁNEA - $70



                  Tradicional Ensalada Mediterránea con Aceituna Negra y Crotones,
                  con Aderezo de Menta.]]></page><page Index="7"><![CDATA[Sopas

















                                                                 SOPA DE TORTILLA - $60
                                                                 Quesadillitas rellenas de Queso y
                                                                 Epazote bañadas en Salsa cremosa de
                                                                 Jitomate, Crema, Queso y Aguacate.


                                                                 CALDO TLALPEÑO - $60
                                                                 Tradicional Caldo Tlalpeño con
                                                                 Verduras y Pollo coronado con un
                                                                 Chile Chipotle.























         SOPA DE CEBOLLA - $50
         Clásica Sopa de Cebolla y Poro
         acompañada con un Crotón
         gratinado.


         CREMA BICOLOR - $70
         Dualidad de crema de zanahoria y
         calabaza acompañada de crotones]]></page><page Index="8"><![CDATA[Menu Infantil














                  HAMBURGUESA DE NIÑOS - $80
                  Clásica Hamburguesa con Queso, Lechuga, Jitomate y Cebolla.
                  Acompañada de papas a la francesa



                  NUGGETS - $65
                  Acompañados de Papas a la Francesa y Salsa de Tomate.




                  CAMARONES ROCA
                  Camarones empanizados acompañado de papas a la francesa.]]></page><page Index="9"><![CDATA[Aves









                   PECHUGA ZARANDEADA - $100
                   Pechuga al Grill Salseada con Zarandeada Guarniciones a Elegir (2
                   opciones)




                   PECHUGA CORDON BLEU - $100
                   Clasica Pechuga Rellena con Queso Mozarella y Jamón,
                   Empanizada y Bañada en Salsa Bechamel
                   Guarniciones a Elegir (2 opciones)




                   PECHUGA AL VINO BLANCO - $100
                   Pechuga a la Plancha Bañada en Salsa de Vino Blanco
                   Guarniciones a Elegir (2 opciones)]]></page><page Index="10"><![CDATA[Cortes














































                   RIB-EYE - $250



                   NEW YORK - $280


                   ARRACHERA - $250


                   FILETE MAR Y TIERRA - $200


                   CHAMORRO ADOBADO - $180


                                                                                       Guarniciones:

                                                     • Risotto • Ensalada mixta • Queso asado
                                                              • Papa del día • Verduras grilladas

                                         Guarniciones extra $30 cada una.]]></page><page Index="11"><![CDATA[Mariscos













                                                                PULPO ZARANDEADO - $200
                                                                Pulpo al Grill Salseado con Zarandeada
                                                                Guarniciones a Elegir (2 opciones)


                                                                CAMARONES AL GUSTO - $150
                                                                Al Mojo de Ajo, al Ajillo, a la
                                                                Mantequilla, Guarniciones a Elegir (2
                                                                opciones)

                                                                PULPO EN COSTRA DE
                                                                CHICHARRÓN - $160
                                                                Pulpo en costra de chicharrón con un
                                                                Cremoso de Aguacate, Guarniciones a
                                                                Elegir (2 opciones)




                                   Pescados












           SALMON EN SALSA DE MIEL
           MOSTAZA - $150
           Salmon bañado en Salsa Miel Mostaza
           con una Costra de Parmesano
           Guarniciones a Elegir (2 opciones)


           SALMON A LA PLANCHA - $150
           Salmon a la Plancha o las Finas Hierbas
           Guarniciones a Elegir (2 opciones)

           MERO PAPILLOTE - $100
           Mero Empapelado con Arroz y Verduras
           al Vapor acompañado con Ensalada de
           la Casa]]></page><page Index="12"><![CDATA[Bebidas
                                        B         e     b      id       a      s










             MOJITOS - $45                                     CLAYTON PUSSY FOOT - $45
             De Piña, Fresa o Pepino, con hojas frescas        Punch de Piña, Naranja y Uva con un toque
             de Yerbabuena, un toque de Limón y                de Granadina.
             Azúcar, top de Agua Mineral o Ginger Ale.
                                                               MARGARITA VIRGEN  - $45
             PIÑATA - $45                                      Twister Frozen de Naranja y Limón, realzado
             Cubitos de Fresa y Piña martajados en             con Sal y Azúcar.
             jugo de Limón y Yerbabuena, top de Jugo
             de Naranja.                                       SHERLEY TEMPLE - $45
                                                               Jugo de Naranja con un toque de Limón y
             TROPICAL TOWER - $45                              Granadina, top de Agua Mineral y un guiño
             Punch de Mango y Durazno con cubitos              de Marraschino.
             de Pepino y Piña, martajados en jugo de
             Limón.                                            GREEN APPLE SPARKLE - $45
                                                               Lajas de Manzana y Cuñas de Limón con
             SANGRÍA INVERTIDA  - $45                          un toque de Azúcar, top de Agua Mineral,
             Split de Limonada con jugo de Uva.                Sprite o Ginger Ale.

             CAIPIRINHA VIRGEN - $45
             Cuñas de Limón martajadas con hojas
             frescas de Yerbabuena y un toque de
             Azúcar, top de Ginger Ale.]]></page><page Index="13"><![CDATA[B         e     b      id       a      s
                                        Bebidas










                TÉ HELADO - $45
                De tu preferencia con Hielos, endulzado a tu gusto.

                LICUADO O FRAPPE - $50
                Fresa, Plátano, Papaya, Manzana con Granola, Chocolate de la Abuela

                CHOCOLATE - $35
                Frio o caliente con leche entera o deslactosada.

                CAFÉ CON LECHE - $45


                Media taza de Café y media taza de Leche entera o deslactosada.

                CAPUCCINO - $35
                Cremoso, Espumoso, Delicioso.

                FRAPUCCINO - $35
                Licuado con Hielo, endulzado con Azúcar.

                • Café Americano o Descafeinado - $25
                • Jugo de Naranja  - $25
                • Jugo Verde  - $25
                • Naranjada y Limonada - $25
                • Jarra de Limonada o Naranjada  - $80
                • Refrescos  - $25]]></page><page Index="14"><![CDATA[Proyecto






                                                               de la































































                 @universidaduno.mexico




                 @universidaduno.mexico]]></page></pages></Search>